snitch_ai/__init__.py
snitch_ai/cert/snitch.localapi.crt
snitch_ai/internal/__init__.py
snitch_ai/internal/analysis_status.py
snitch_ai/internal/api_client.py
snitch_ai/internal/drift_analysis.py
snitch_ai/internal/guid.py
snitch_ai/internal/logger.py
snitch_ai/internal/project.py
snitch_ai/internal/quality_analysis.py
snitch_ai-1.1.13.dist-info/METADATA
snitch_ai-1.1.13.dist-info/WHEEL
snitch_ai-1.1.13.dist-info/top_level.txt
snitch_ai-1.1.13.dist-info/RECORD
