Metadata-Version: 2.1
Name: snitch-ai
Version: 1.1.13
Summary: Client library for using Snitch AI's model validation platform
Home-page: https://snit.ch
Author: Snitch AI
Author-email: info@snit.ch
License: UNKNOWN
Platform: UNKNOWN
Classifier: Programming Language :: Python
Classifier: Programming Language :: Python :: 3
Classifier: Programming Language :: Python :: 3.8
Requires-Dist: requests (>=2)
Requires-Dist: requests-toolbelt (>=0.9)
Requires-Dist: joblib (>=1)
Requires-Dist: numpy (>=1)
